LICENSE
MANIFEST.in
README.md
requirements.txt
setup.cfg
setup.py
version.txt
lmchallenge/__init__.py
lmchallenge/__main__.py
lmchallenge/diff.py
lmchallenge/grep.py
lmchallenge/log.schema
lmchallenge/pretty.py
lmchallenge/run.py
lmchallenge/stats.py
lmchallenge/validate.py
lmchallenge.egg-info/PKG-INFO
lmchallenge.egg-info/SOURCES.txt
lmchallenge.egg-info/dependency_links.txt
lmchallenge.egg-info/entry_points.txt
lmchallenge.egg-info/requires.txt
lmchallenge.egg-info/top_level.txt
lmchallenge/core/__init__.py
lmchallenge/core/common.py
lmchallenge/core/errors.py
lmchallenge/core/model.py
lmchallenge/core/reranking.py
lmchallenge/data/viewer.css
lmchallenge/data/viewer.html
lmchallenge/data/viewer.js