Metadata-Version: 1.0
Name: lmchallenge
Version: 5.0
Summary: LM Challenge - A library & tools to evaluate predictive language models.
Home-page: https://github.com/Microsoft/LMChallenge
Author: Microsoft Corporation
Author-email: swiftkey-deep@service.microsoft.com
License: MIT
Platform: UNKNOWN
